awsSchema/S3.py
awsSchema/__init__.py
awsSchema/_nbdev.py
awsSchema/apigateway.py
awsSchema/cloudfront.py
awsSchema/cloudfrontSchema.py
awsSchema/dynamodb.py
awsSchema-0.0.27.dist-info/LICENSE
awsSchema-0.0.27.dist-info/METADATA
awsSchema-0.0.27.dist-info/WHEEL
awsSchema-0.0.27.dist-info/entry_points.txt
awsSchema-0.0.27.dist-info/top_level.txt
awsSchema-0.0.27.dist-info/RECORD
