Metadata-Version: 2.1
Name: awsSchema
Version: 0.0.27
Summary: dataclasss for parsing aws objects eg api-gateway proxy integration proy
Home-page: https://github.com/thanakijwanavit/awsSchema/tree/master/
Author: nic wanavit
Author-email: nwanavit@hatari.cc
License: Apache Software License 2.0
Keywords: aws schema dataclass
Platform: UNKNOWN
Classifier: Development Status :: 3 - Alpha
Classifier: Intended Audience :: Developers
Classifier: License :: OSI Approved :: Apache Software License
Classifier: Natural Language :: English
Classifier: Programming Language :: Python :: 3.6
Classifier: Programming Language :: Python :: 3.7
Classifier: Programming Language :: Python :: 3.8
Requires-Python: >=3.6
Requires-Dist: dataclasses-json
Requires-Dist: ujson
